jeig/__init__.py
jeig/jeig.py
jeig/py.typed
jeig-0.5.1.dist-info/licenses/LICENSE
jeig-0.5.1.dist-info/METADATA
jeig-0.5.1.dist-info/WHEEL
jeig-0.5.1.dist-info/top_level.txt
jeig-0.5.1.dist-info/RECORD
