Metadata-Version: 2.4
Name: jeig
Version: 0.5.1
Summary: Various eigendecomposition implementations wrapped for jax.
Author-email: Martin Schubert <mfschubert@gmail.com>
Maintainer-email: Martin Schubert <mfschubert@gmail.com>
License-Expression: BSD-3-Clause
Keywords: jax,eigendecomposition,eig,torch,scipy,numpy
Requires-Python: >=3.7
License-File: LICENSE
Requires-Dist: jax>=0.4.36
Requires-Dist: jaxlib
Requires-Dist: numpy
Requires-Dist: packaging
Requires-Dist: scipy
Requires-Dist: torch
Provides-Extra: tests
Requires-Dist: parameterized; extra == "tests"
Requires-Dist: pytest; extra == "tests"
Requires-Dist: pytest-cov; extra == "tests"
Provides-Extra: dev
Requires-Dist: bump-my-version; extra == "dev"
Requires-Dist: darglint; extra == "dev"
Requires-Dist: jeig[tests]; extra == "dev"
Requires-Dist: matplotlib; extra == "dev"
Requires-Dist: mypy; extra == "dev"
Requires-Dist: pre-commit; extra == "dev"
Dynamic: license-file
